pywidevine/__init__.py
pywidevine/cdm.py
pywidevine/device.py
pywidevine/exceptions.py
pywidevine/key.py
pywidevine/license_protocol.proto
pywidevine/license_protocol_pb2.py
pywidevine/license_protocol_pb2.pyi
pywidevine/main.py
pywidevine/pssh.py
pywidevine/remotecdm.py
pywidevine/serve.py
pywidevine/session.py
pywidevine/utils.py
pywidevine-1.7.0.dist-info/LICENSE
pywidevine-1.7.0.dist-info/METADATA
pywidevine-1.7.0.dist-info/WHEEL
pywidevine-1.7.0.dist-info/entry_points.txt
pywidevine-1.7.0.dist-info/RECORD
