Metadata-Version: 2.1
Name: pywidevine
Version: 1.7.0
Summary: Widevine CDM (Content Decryption Module) implementation in Python.
Home-page: https://github.com/devine-dl/pywidevine
License: GPL-3.0-only
Keywords: python,drm,widevine,google
Author: rlaphoenix
Author-email: rlaphoenix@pm.me
Requires-Python: >=3.7,<4.0
Classifier: Development Status :: 5 - Production/Stable
Classifier: Intended Audience :: Developers
Classifier: Intended Audience :: End Users/Desktop
Classifier: License :: OSI Approved :: GNU General Public License v3 (GPLv3)
Classifier: Natural Language :: English
Classifier: Operating System :: OS Independent
Classifier: Programming Language :: Python :: 3
Classifier: Programming Language :: Python :: 3.7
Classifier: Programming Language :: Python :: 3.8
Classifier: Programming Language :: Python :: 3.9
Classifier: Programming Language :: Python :: 3.10
Classifier: Programming Language :: Python :: 3.11
Classifier: Topic :: Multimedia :: Video
Classifier: Topic :: Security :: Cryptography
Classifier: Topic :: Software Development :: Libraries :: Python Modules
Provides-Extra: serve
Requires-Dist: PyYAML (>=6.0.1,<7.0.0) ; extra == "serve"
Requires-Dist: Unidecode (>=1.3.7,<2.0.0)
Requires-Dist: aiohttp (>=3.8.6,<4.0.0) ; extra == "serve"
Requires-Dist: click (>=8.1.7,<9.0.0)
Requires-Dist: protobuf (>=4.24.4,<5.0.0)
Requires-Dist: pycryptodome (>=3.19.0,<4.0.0)
Requires-Dist: pymp4 (>=1.4.0,<2.0.0)
Requires-Dist: requests (>=2.31.0,<3.0.0)
Project-URL: Changelog, https://github.com/devine-dl/pywidevine/blob/master/CHANGELOG.md
Project-URL: Discussions, https://github.com/devine-dl/pywidevine/discussions
Project-URL: Issues, https://github.com/devine-dl/pywidevine/issues
Project-URL: Repository, https://github.com/devine-dl/pywidevine
